dataprep/__init__.py
dataprep/admin_boundaries.py
disruptsc_dataprep-1.0.1.dist-info/METADATA
disruptsc_dataprep-1.0.1.dist-info/WHEEL
disruptsc_dataprep-1.0.1.dist-info/top_level.txt
disruptsc_dataprep-1.0.1.dist-info/RECORD
