Metadata-Version: 2.1
Name: disruptsc-dataprep
Version: 1.0.1
Summary: Tools to help prepare data for the DisruptSC model.
Home-page: https://github.com/ccolon/disruptsc-dataprep
Author: Celian Colon
Author-email: celian.colon.2007@polytechnique.org
License: CC BY-NC-ND 4.0
Classifier: Programming Language :: Python :: 3
Classifier: License :: Other/Proprietary License
Classifier: Operating System :: OS Independent
Requires-Python: >=3.10
Requires-Dist: gadm ==0.0.5
